ssg/__init__.py
ssg/app.py
myssg-0.2.1.dist-info/entry_points.txt
myssg-0.2.1.dist-info/LICENSE
myssg-0.2.1.dist-info/WHEEL
myssg-0.2.1.dist-info/METADATA
myssg-0.2.1.dist-info/RECORD
