Metadata-Version: 2.1
Name: myssg
Version: 0.2.1
Summary: 
Home-page: https://github.com/tranvietphuoc/ssg
License: MIT
Author: Tran Viet Phuoc
Author-email: phuoc.finn@gmail.com
Requires-Python: >=3.9,<4.0
Classifier: License :: OSI Approved :: MIT License
Classifier: Programming Language :: Python :: 3
Classifier: Programming Language :: Python :: 3.10
Classifier: Programming Language :: Python :: 3.9
Requires-Dist: Jinja2 (>=3.0.1,<4.0.0)
Requires-Dist: PyYAML (>=6.0,<7.0)
Requires-Dist: click (>=8.1.3,<9.0.0)
Requires-Dist: debugpy (>=1.5.0,<2.0.0)
Requires-Dist: markdown2 (>=2.4.1,<3.0.0)
Requires-Dist: pytest (>=7.2.0,<8.0.0)
Project-URL: Repository, https://github.com/tranvietphuoc/ssg
